{
  "ЛЮДИ": {
    "37QUEEN": "👑 Как вы думаете, какая девушка в этом году заслужила номинацию королевы нашей премии?",
    "37KING": "🤴 Какой парень удостоился номинации короля на нашей премии?",
    "ЧЕЛОВЕК-МЕМ ГОДА": "😂 С каким человеком появилось больше всего смешных мемов за год?",
    "ФРИК ГОДА": "🎭 Кто в этом году выделился своим нестандартным поведением?",
    "📋 Список номинаций": "🎯 Номинация: 📋 Список номинаций"
  },
  "МЕМЫ": {
    "МЕМ ГОДА": "📸 Какой мем показался вам самым смешным в этом году?"
  }
}